odoo/addons/partner_credit_limit_history/README.rst
odoo/addons/partner_credit_limit_history/__init__.py
odoo/addons/partner_credit_limit_history/__manifest__.py
odoo/addons/partner_credit_limit_history/i18n/es.po
odoo/addons/partner_credit_limit_history/i18n/partner_credit_limit_history.pot
odoo/addons/partner_credit_limit_history/models/__init__.py
odoo/addons/partner_credit_limit_history/models/res_partner.py
odoo/addons/partner_credit_limit_history/readme/CONTRIBUTORS.rst
odoo/addons/partner_credit_limit_history/readme/DESCRIPTION.rst
odoo/addons/partner_credit_limit_history/readme/USAGE.rst
odoo/addons/partner_credit_limit_history/security/ir.model.access.csv
odoo/addons/partner_credit_limit_history/static/description/icon.png
odoo/addons/partner_credit_limit_history/static/description/index.html
odoo/addons/partner_credit_limit_history/tests/__init__.py
odoo/addons/partner_credit_limit_history/tests/test_partner_credit_limit.py
odoo/addons/partner_credit_limit_history/views/res_partner_view.xml
odoo/addons/partner_credit_limit_history/wizard/__init__.py
odoo/addons/partner_credit_limit_history/wizard/partner_credit_limit_wizard.py
odoo/addons/partner_credit_limit_history/wizard/partner_credit_limit_wizard.xml
odoo13_addon_partner_credit_limit_history-13.0.1.0.1.dev3.dist-info/METADATA
odoo13_addon_partner_credit_limit_history-13.0.1.0.1.dev3.dist-info/WHEEL
odoo13_addon_partner_credit_limit_history-13.0.1.0.1.dev3.dist-info/top_level.txt
odoo13_addon_partner_credit_limit_history-13.0.1.0.1.dev3.dist-info/RECORD
